pd_sql_loader/__init__.py
pd_sql_loader/sql_load.py
pd_sql_loader/pandas_sql_loader/__init__.py
pd_sql_loader/pandas_sql_loader/downcast.py
pd_sql_loader/pandas_wrapper/__init__.py
pd_sql_loader/pandas_wrapper/from_records.py
pd_sql_loader/pandas_wrapper/read_db.py
pd_sql_loader/pandas_wrapper/read_sql.py
pd_sql_loader/pandas_wrapper/read_sqlite.py
pd_sql_loader/pandas_wrapper/read_table.py
pd_sql_loader/pandas_wrapper/to_arrays.py
pd_sql_loader/pandas_wrapper/wrap_result.py
pd_sql_loader-1.4.2.dist-info/METADATA
pd_sql_loader-1.4.2.dist-info/WHEEL
pd_sql_loader-1.4.2.dist-info/top_level.txt
pd_sql_loader-1.4.2.dist-info/RECORD
